saipyhelper/__init__.py
saipyhelper/bitmap.py
saipyhelper/json.py
saipyhelper/string.py
saipyhelper-0.0.1.dist-info/LICENSE
saipyhelper-0.0.1.dist-info/METADATA
saipyhelper-0.0.1.dist-info/WHEEL
saipyhelper-0.0.1.dist-info/top_level.txt
saipyhelper-0.0.1.dist-info/RECORD
