Metadata-Version: 2.1
Name: saipyhelper
Version: 0.0.1
Summary: A common package powered by python3
Author-email: 13sai <sai210718@gmail.com>
Project-URL: Homepage, https://github.com/13sai/pyhelper
Project-URL: Bug Tracker, https://github.com/13sai/pyhelper/issues
Classifier: Programming Language :: Python :: 3
Classifier: License :: OSI Approved :: MIT License
Classifier: Operating System :: OS Independent
Requires-Python: >=3.5
License-File: LICENSE
